README.md
setup.py
QBall/__init__.py
QBall/interpreter.py
QBall/lexer.py
QBall/token.py
qball_lang.egg-info/PKG-INFO
qball_lang.egg-info/SOURCES.txt
qball_lang.egg-info/dependency_links.txt
qball_lang.egg-info/requires.txt
qball_lang.egg-info/top_level.txt