Metadata-Version: 2.1
Name: qball-lang
Version: 0.5.5
Summary: QBall is a high level interpreted language. This is a Python module for using QBall in python programs. Source: https://github.com/KingsleyDockerill/QBall
Home-page: UNKNOWN
License: UNKNOWN
Platform: UNKNOWN
Requires-Python: >=3.6.3
